.cruft.json
.gitignore
.pre-commit-config.yaml
CHANGES.rst
CITATION.cff
CODE_OF_CONDUCT.md
CONTRIBUTING.md
LICENSE
MANIFEST.in
README.rst
codespell-ignore.txt
pyproject.toml
setup.py
tox.ini
.github/CODEOWNERS
.github/dependabot.yml
.github/labeler.yml
.github/ISSUE_TEMPLATE/FEATURE_REQUEST.md
.github/ISSUE_TEMPLATE/ISSUE_TEMPLATE.md
.github/ISSUE_TEMPLATE/PR_TEMPLATE.md
.github/workflows/changelog.yml
.github/workflows/run_labeler.yml
.github/workflows/run_snappl_tests.yml
.github/workflows/sphinx-deploy.yml
.github/workflows/sub_package_update.yml
changes/.gitkeep
changes/10.snappl.rst
changes/103.snappl.rst
changes/105.docs.rst
changes/106.docs.rst
changes/107.feature.rst
changes/109.bugfix.rst
changes/111.docs.rst
changes/112.snappl.rst
changes/116.docs.rst
changes/118.feature.rst
changes/120.feature.rst
changes/122.feature.rst
changes/124.bugfix.rst
changes/127.bugfix.rst
changes/13.bugfix.rst
changes/130.bugfix.rst
changes/131.snappl.rst
changes/132.snappl.rst
changes/138.feature.rst
changes/14.snappl.rst
changes/140.bugfix.rst
changes/145.bugfix.rst
changes/146.snappl.rst
changes/147.bugfix.rst
changes/15.feature.rst
changes/150.snappl
changes/153.snappl.rst
changes/155.bugfix.rst
changes/156.feature.rst
changes/158.snappl.rst
changes/159.snappl.rst
changes/16.feature.rst
changes/160.feature.rst
changes/163.bugfix.rst
changes/164.snappl.rst
changes/18.feature.rst
changes/20.bugfix.rst
changes/23.snappl.rst
changes/26.feature.rst
changes/29.feature.rst
changes/3.snappl.rst
changes/31.feature.rst
changes/35.snappl.rst
changes/36.snappl.rst
changes/37.snappl.rst
changes/40.snappl.rst
changes/41.snappl.rst
changes/43.snappl.rst
changes/47.feature.rst
changes/49.docs.rst
changes/5.snappl.rst
changes/54.snappl.rst
changes/57.snappl.rst
changes/58.snappl.rst
changes/61.bugfix.rst
changes/62.snappl.rst
changes/63.snappl.rst
changes/65.bugfix.rst
changes/68.feature.rst
changes/72.snappl.rst
changes/73.feature.rst
changes/74.bugfix.rst
changes/79.snappl.rst
roman_snpit_snappl.egg-info/PKG-INFO
roman_snpit_snappl.egg-info/SOURCES.txt
roman_snpit_snappl.egg-info/dependency_links.txt
roman_snpit_snappl.egg-info/not-zip-safe
roman_snpit_snappl.egg-info/requires.txt
roman_snpit_snappl.egg-info/top_level.txt
