Metadata-Version: 2.4
Name: roman_snpit_snappl
Version: 0.37.0
Summary: General, database, and photometry utilities for the Roman SNPIT
Author: Roman Supernova Project Infrastructure Team
Maintainer-email: Roman SN PIT <raknop@lbl.gov>
Project-URL: repository, https://github.com/Roman-Supernova-PIT
Classifier: Development Status :: 3 - Alpha
Classifier: Programming Language :: Python
Requires-Python: >=3.11
License-File: LICENSE
Requires-Dist: astropy<8.0.0,>=7.1.0
Requires-Dist: fitsio<2.0.0,>=1.2.5
Requires-Dist: galsim<3.0.0,>=2.7.2
Requires-Dist: gwcs<0.27.0,>=0.26.0
Requires-Dist: h5py<4.0.0,>=3.14.0
Requires-Dist: numpy<3.0.0,>=2.2.6
Requires-Dist: pandas<3.0.0,>=2.3.3
Requires-Dist: photutils<3.0.0,>=2.3.0
Requires-Dist: pycryptodome<4.0.0,>=3.23.0
Requires-Dist: python-dateutil<3.0.0,>=2.9.0.post0
Requires-Dist: pytz>=2025.2
Requires-Dist: pyyaml<7.0.0,>=6.0.3
Requires-Dist: rkwebutil<3.0.0,>=2.5.0
Requires-Dist: roman-datamodels<0.28.0,>=0.27.0
Requires-Dist: scipy<2.0.0,>=1.16.2
Requires-Dist: simplejson<4.0.0,>=3.20.2
Provides-Extra: test
Requires-Dist: pytest; extra == "test"
Requires-Dist: pytest-doctestplus; extra == "test"
Requires-Dist: pytest-cov; extra == "test"
Requires-Dist: requests; extra == "test"
Requires-Dist: tox; extra == "test"
Requires-Dist: devpi_process; extra == "test"
Requires-Dist: psycopg<4.0.0,>=3.2.9; extra == "test"
Provides-Extra: docs
Requires-Dist: sphinx; extra == "docs"
Requires-Dist: sphinx-automodapi; extra == "docs"
Requires-Dist: matplotlib; extra == "docs"
Requires-Dist: sphinx; extra == "docs"
Requires-Dist: mock; extra == "docs"
Requires-Dist: tomli; extra == "docs"
Requires-Dist: graphviz; extra == "docs"
Dynamic: license-file
